Lab 09/Ejercicio 02/Modulos2.v
//Nicole Prem 18337 Ejercicio 02 del lab 09

//FF tipo D:
module FFD1 (input clk, reset, D, enable, output reg salida); 
always @(posedge clk, posedge reset )
begin
    if (reset)
    salida <= 'b0;
    else if (enable && clk)
    salida <= D;
end
endmodule 

//FF tipo T
module FFT(input clk, reset, enable, output wire salidaT);
wire E;
reg M;
FFD1 FT(clk, reset, E, enable, salidaT);
always @(posedge clk)
begin
    assign M=~salidaT;
end
assign E=M;
endmodule

Lab 09/Ejercicio 02/Modulos2_tb.v
//Nicole Prem 18337 testbench ejercicio 02 del lab 09

module Testbench();

always begin #2 clk = ~clk; end

reg clk, reset, enable;
wire salidaT;
FFT FT(clk, reset, enable, salidaT);

initial begin
$display ("\n");
$display ("Ejercicio 02: FF tipo T");
$display ("clk reset enable | salida");
$display ("------------------------------|-------");
$monitor ("%b %b %b | %b", clk, reset, enable, salidaT);

clk=0; reset=0; enable=0;
#5 reset=1;
#5 reset=0;
#5 enable=1;
#15 $finish;
end

initial begin
    $dumpfile ("Modulos2_tb.vcd");
    $dumpvars (0, Testbench);
end

endmodule

Lab 09/Ejercicio 02/Modulos2_tb.vcd
$date
	Sat Oct 31 10:38:49 2020
$end
$version
	Icarus Verilog
$end
$timescale
	1ps
$end
$scope module Testbench $end
$var wire 1 ! salidaT $end
$var reg 1 " clk $end
$var reg 1 # enable $end
$var reg 1 $ reset $end
$scope module FT $end
$var wire 1 % E $end
$var wire 1 " clk $end
$var wire 1 # enable $end
$var wire 1 $ reset $end
$var wire 1 ! salidaT $end
$var reg 1 & M $end
$scope module FT $end
$var wire 1 % D $end
$var wire 1 " clk $end
$var wire 1 # enable $end
$var wire 1 $ reset $end
$var reg 1 ! salida $end
$upscope $end
$upscope $end
$upscope $end
$enddefinitions $end
#0
$dumpvars
x&
x%
0$
0#
0"
x!
$end
#2
1"
#4
0"
#5
0!
1$
#6
1%
1&
1"
#8
0"
#10
1"
0$
#12
0"
#14
1"
#15
1#
#16
0"
#18
1!
1"
#20
0"
#22
0!
0%
0&
1"
#24
0"
#26
1!
1%
1&
1"
#28
0"
#30
0!
0%
0&
1"
