Lab 09/Ejercicio 03/Modulos3.v
//Nicole Prem 18337 ejercicio 03 del lab 09

module FFD1 (input clk, reset, D, enable, output reg salida); 
always @(posedge clk, posedge reset )
begin
    if (reset)
    salida <= 'b0;
    else if (enable && clk)
    salida <= D;
end
endmodule 



//FF tipo JK
module FFJK (input clk, reset, J, K, enable, output salidaJK);
    wire A1, A2, A3, A4, A5;
    FFD1 FD(clk, reset, A1, enable, salidaJK);
    not N1(A2, salidaJK);
    nand NA1(A3, J, A2);
    not N2(A4, K);
    nand NA2(A5, A4, salidaJK);
    nand NA3(A1, A5, A3);

endmodule

Lab 09/Ejercicio 03/Modulos3_tb.v
//Nicole Prem 18337 testbench ejercicio 03 del lab 09

module Testbench();

always begin #2 clk = ~clk; end

reg clk, reset, enable, J, K;
wire salidaJK;
FFJK FJK(clk, reset, J, K, enable, salidaJK);

initial begin
$display ("\n");
$display ("Ejercicio 03: FF tipo JK");
$display ("clk reset J K enable | salida");
$display ("------------------------------|-------");
$monitor ("%b %b %b %b %b| %b", clk, reset, J, K, enable, salidaJK);

clk=0; reset=0; enable=0; J=0; K=0;
#5 reset=1;
#5 reset=0;
#5 enable=1;
#5 J=1;
#5 J=0;
#5 K=1;
#5 J=1;
#15 $finish;
end

initial begin
    $dumpfile ("Modulos3_tb.vcd");
    $dumpvars (0, Testbench);
end

endmodule

Lab 09/Ejercicio 03/Modulos3_tb.vcd
$date
	Sat Oct 31 11:43:20 2020
$end
$version
	Icarus Verilog
$end
$timescale
	1ps
$end
$scope module Testbench $end
$var wire 1 ! salidaJK $end
$var reg 1 " J $end
$var reg 1 # K $end
$var reg 1 $ clk $end
$var reg 1 % enable $end
$var reg 1 & reset $end
$scope module FJK $end
$var wire 1 ' A1 $end
$var wire 1 ( A2 $end
$var wire 1 ) A3 $end
$var wire 1 * A4 $end
$var wire 1 + A5 $end
$var wire 1 " J $end
$var wire 1 # K $end
$var wire 1 $ clk $end
$var wire 1 % enable $end
$var wire 1 & reset $end
$var wire 1 ! salidaJK $end
$scope module FD $end
$var wire 1 ' D $end
$var wire 1 $ clk $end
$var wire 1 % enable $end
$var wire 1 & reset $end
$var reg 1 ! salida $end
$upscope $end
$upscope $end
$upscope $end
$enddefinitions $end
#0
$dumpvars
x+
1*
1)
x(
x'
0&
0%
0$
0#
0"
x!
$end
#2
1$
#4
0$
#5
0'
1+
1(
0!
1&
#6
1$
#8
0$
#10
1$
0&
#12
0$
#14
1$
#15
1%
#16
0$
#18
1$
#20
1'
0)
0$
1"
#22
1)
0+
0(
1!
1$
#24
0$
#25
0"
#26
1$
#28
0$
#30
0'
1+
0*
1$
1#
#32
0$
#34
1(
0!
1$
#35
1'
0)
1"
#36
0$
#38
0'
1)
0(
1!
1$
#40
0$
#42
1'
0)
1(
0!
1$
#44
0$
#46
0'
1)
0(
1!
1$
#48
0$
#50
1'
0)
1(
0!
1$
