Lab #04/ModulosLab03.v
//Nicole Prem 18337

module Tabla01_Ej1 (input wire A01, B01, C01, output wire Y01); //Variables para la tabla 01 del ej 1

wire notA01, notB01, notC01, out01, out02, out03; //Ecuación a implementar: Y01 = (A01'& C01') | (A01& & C01) | (A01 & B01') 

not NotA01 (notA01, A01);
not NotB01 (notB01, B01);
not NotC01 (notC01, C01);

and And01 (out01, notA01, notC01);
and And02 (out02, A01, C01);
and And03 (out03, A01,notB01);
or Or1 (Y01, out01, out02, out03);

endmodule

module Tabla02_Ej1 (input wire B02, output wire Y02); //Variables para la tabla 02 del ej 1

not NotB01 (Y02, B02);

endmodule 

module Tabla03_Ej1 (input wire A03, B03, C03, D03, output wire Y03); //Variables tabla 03 del ej 1

assign Y03 = (~A03 & ~B03 & ~C03 & ~D03) | (A03 & B03 & ~C03 & ~D03) | (~A03 & B03 & ~C03 & D03) | (A03 & ~B03 & ~C03 & D03) | (~A03 & ~B03 & C03 & D03) |
            (A03 & B03 & C03 & D03) | (~A03 & B03 & C03 & ~D03) | (A03 & ~B03 & C03 & ~D03);

endmodule 

module Tabla04_Ej1 (input wire A04, B04, C04, D04, output wire Y04); //Variables tabla 04 del ej 1

assign Y04 = (A04 & B04) | (A04 & C04) | (A04 & ~C04 & ~D04);

endmodule 

module Tabla1_Ej2 (input wire A11, B11, C11, D11, output wire Y11); //Variables tabla 1 del ej 2

assign Y11 = (A11 & ~C11) | (~B11 & ~C11 & ~D11) | (A11 & ~B11) | (A11 & C11 & ~D11);

endmodule 

module Tabla2_Ej2 (input wire C12, B12, output wire Y12); //Variables tabla 2 ej 2

wire notB12;

not NotB12 (notB12, B12);

or Or12 (Y12, notB12, C12);

endmodule

module Tabla3_Ej2 (input wire A13, B13, C13, D13, output wire Y13); //Variables tabla 3 del ej 2

assign Y13 = (~B13 & ~C13 & D13) | (B13) | (A13 & ~B13 & D13);

endmodule 

module Tabla4_Ej2 (input wire A14, B14, C14, output wire Y14); //Variables tabla 4 del ej 2

wire notA14, notC14, out11;

not NotA14 (notA14, A14);
not NotC14 (notC14, C14);

and And14 (out11, notA14, notC14);

or Or14 (Y14, out11, B14);

endmodule


// ----------------------------------------------- Desde aquí empieza el ejercicio 5 ---------------------------------------------------


module TablaSOP_Ej5_GLM (input wire A5, B5, output wire Y5); //variables de la ecuacuación SOP del ej 5, GLM = gate level modelling

wire notA5, notB5, out5, out6, out7;

not NotA5 (notA5, A5);
not NotB5 (notB5, B5);

and And5 (out5, notA5, B5);
and And6 (out6, A5, notB5);
and And7 (out7, A5, B5);
or Or5 (Y5, out5, out6, out7);

endmodule 

module TablaPOS_Ej5_GLM (input wire A05, B05, output wire Y05); //variables ecuación POS del ej 5, GLM

or Or05 (Y05, A05, B05);

endmodule

module KMap_GLM (input wire A15, B15, output wire Y15); // variables de la ecuación obtenida del K-Map del ej 5, GLM

or Or15 (Y15, A15, B15);

endmodule 

module TablaSOP_Ej5_BM (input wire A25, B25, output wire Y25); // variables de la ecuación SOP del ej 5, BM = behavioral modelling

assign Y25 = (~A25 & B25) | (A25 & ~B25) | (A25 & B25);

endmodule

module TablaPOS_Ej5_BM (input wire A35, B35, output wire Y35); // variables de la ecuación POS del ej 5, BM

assign Y35 = (A35 & B35);

endmodule

module KMap_BM (input wire A45, B45, output wire Y45); // variables de la ecuación del K-Map del ej 5, BM

assign Y45 = (A45 & B45);

endmodule

Lab #04/ModulosLab03_tb.v
// Nicole Prem 18337 Testbench de los Modulos

module testbench();
reg A01, B01, C01, B02, A03, B03, C03, D03, A04, B04, C04, D04, A11, B11, C11, D11, C12, B12, A13, B13, C13, D13, A14, B14, C14, A5, B5, A05, B05, 
    A15, B15, A25, B25, A35, B35, A45, B45; //todos los inputs
wire Y01, Y02, Y03, Y04, Y11, Y12, Y13, Y14, Y5, Y05, Y15, Y25, Y35, Y45; //todos los outputs

Tabla01_Ej1 T01 (A01, B01, C01, Y01); //Tabla 01

initial begin
$display("Tabla 01");
$display ("A B C | Y");
$display ("------|---");
$monitor ("%b %b %b | %b", A01, B01, C01, Y01);

A01 = 0; B01 = 0; C01 = 0; //1

#1 C01=1; //2
#1 B01=1; C01=0; //3
#1 C01=1; //4
#1 A01=1; B01=0; C01=0; //5
#1 C01=1; //6
#1 B01=1; C01=0; //7
#1 C01=1; //8
end
 
Tabla02_Ej1 T02 (B02, Y02); //Tabla 02

initial begin
    #10
$display ("Tabla 02");
$display ("B | Y");
$display ("--|---");
$monitor ("%b | %b",B02, Y02);

B02=0;
#1 B02 = 1;

end

Tabla03_Ej1 T03 (A03, B03, C03, D03, Y03); //Tabla 03

initial begin 
    #15
$display("Tabla 03");
$display("A B C D| Y");
$display ("------|---");
$monitor ("%b %b %b %b | %b", A03, B03, C03, D03, Y03);

A03 = 0; B03 = 0; C03 = 0; D03 = 0; //1

#1 D03 = 1; //2
#1 C03=1; D03=0; //3
#1 D03=1; //4
#1 B03=1; C03=0; D03=0; //5
#1 D03=1; //6
#1 C03=1; D03=0; //7
#1 D03=1; //8
#1 A03=1; B03=0; C03=0; D03=0; //9
#1 D03=1; //10
#1 C03=1; D03=0; //11
#1 D03=1; //12
#1 B03=1; C03=0; D03=0; //13
#1 D03=1; //14
#1 C03=1; D03=0; //15
#1 D03=1; //16

end 

Tabla04_Ej1 T04 (A04, B04, C04, D04, Y04); //Tabla 04

initial begin 
    #35
$display("Tabla 04");
$display("A B C D| Y");
$display ("------|---");
$monitor ("%b %b %b %b | %b", A04, B04, C04, D04, Y04);

A04 = 0; B04 = 0; C04 = 0; D04 = 0; //1

#1 D04 = 1; //2
#1 C04=1; D04=0; //3
#1 D04=1; //4
#1 B04=1; C04=0; D04=0; //5
#1 D04=1; //6
#1 C04=1; D04=0; //7
#1 D04=1; //8
#1 A04=1; B04=0; C04=0; D04=0; //9
#1 D04=1; //10
#1 C04=1; D04=0; //11
#1 D04=1; //12
#1 B04=1; C04=0; D04=0; //13
#1 D04=1; //14
#1 C04=1; D04=0; //15
#1 D04=1; //16

end 

Tabla1_Ej2 T11(A11, B11, C11, D11, Y11); //Tabla 11 (tabla 1 del ej 2)

initial begin 
    #55
$display("Tabla 11");
$display("A B C D| Y");
$display ("------|---");
$monitor ("%b %b %b %b | %b", A11, B11, C11, D11, Y11);

A11 = 0; B11 = 0; C11 = 0; D11 = 0; //1

#1 D11 = 1; //2
#1 C11=1; D11=0; //3
#1 D11=1; //4
#1 B11=1; C11=0; D11=0; //5
#1 D11=1; //6
#1 C11=1; D11=0; //7
#1 D11=1; //8
#1 A11=1; B11=0; C11=0; D11=0; //9
#1 D11=1; //10
#1 C11=1; D11=0; //11
#1 D11=1; //12
#1 B11=1; C11=0; D11=0; //13
#1 D11=1; //14
#1 C11=1; D11=0; //15
#1 D11=1; //16

end 

Tabla2_Ej2 T12(C12, B12, Y12); //Tabla 12 (tabla 2 del ej 2)

initial begin
    #75

$display("Tabla 12");
$display("B C | Y");
$display("----|--");
$monitor("%b %b | %b", B12, C12, Y12);

B12=0; C12=0; 

#1 C12=1;
#1 B12=1; C12=0;
#1 C12=1;


end

Tabla3_Ej2 T13(A13, B13, C13, D13, Y13);

initial begin
    #85

$display("Tabla 13");
$display("A B C D| Y");
$display ("------|---");
$monitor ("%b %b %b %b | %b", A13, B13, C13, D13, Y13);

A13 = 0; B13 = 0; C13 = 0; D13 = 0; //1

#1 D13 = 1; //2
#1 C13=1; D13=0; //3
#1 D13=1; //4
#1 B13=1; C13=0; D13=0; //5
#1 D13=1; //6
#1 C13=1; D13=0; //7
#1 D13=1; //8
#1 A13=1; B13=0; C13=0; D13=0; //9
#1 D13=1; //10
#1 C13=1; D13=0; //11
#1 D13=1; //12
#1 B13=1; C13=0; D13=0; //13
#1 D13=1; //14
#1 C13=1; D13=0; //15
#1 D13=1; //16


end 

Tabla4_Ej2 T14 (A14, B14, C14, Y14);

initial begin
    #107

$display("Tabla 14");
$display ("A B C | Y");
$display ("------|---");
$monitor ("%b %b %b | %b", A14, B14, C14, Y14);

A14 = 0; B14 = 0; C14 = 0; //1

#1 C14=1; //2
#1 B14=1; C14=0; //3
#1 C14=1; //4
#1 A14=1; B14=0; C14=0; //5
#1 C14=1; //6
#1 B14=1; C14=0; //7
#1 C14=1; //8

end
 

//------------------------------ Desde aquí empieza el ejercicio 5 ----------------------------------------------//


TablaSOP_Ej5_GLM T5 (A5, B5, Y5); //ecuación SOP GLM del ej 5

initial begin
    #120

$display("Tabla SOP GLM Ej5");
$display("A B | Y");
$display("----|--");
$monitor ("%b %b | %b", A5, B5, Y5);

A5 = 0; B5 = 0;

#1 B5=1;
#1 A5=1; B5=0;
#1 B5=1;


end

TablaPOS_Ej5_GLM T05 (A05, B05, Y05); //ecuación POS GLM del ej 5

initial begin
    #130

$display("Tabla POS GLM Ej5");
$display("A B | Y");
$display("----|--");
$monitor ("%b %b | %b", A05, B05, Y05);

A05 = 0; B05 = 0;

#1 B05=1;
#1 A05=1; B05=0;
#1 B05=1;


end

KMap_GLM K0(A15, B15, Y15); //ecuación del Kmap del ej 5 GLM

initial begin 
    #140
    
$display("Tabla K-Map GLM Ej5");
$display("A B | Y");
$display("----|--");
$monitor ("%b %b | %b", A15, B15, Y15);

A15 = 0; B15 = 0;

#1 B15=1;
#1 A15=1; B15=0;
#1 B15=1;


end

TablaSOP_Ej5_BM T15 (A25, B25, Y25); // ecuación SOP BM

initial begin 
    #150
    
$display("Tabla POS BM Ej5");
$display("A B | Y");
$display("----|--");
$monitor ("%b %b | %b", A25, B25, Y25);

A25 = 0; B25 = 0;

#1 B25=1;
#1 A25=1; B25=0;
#1 B25=1;

end 

TablaPOS_Ej5_BM T25 (A35, B35, Y35); //ecuación POS BM

initial begin 
    #160
    
$display("Tabla SOP BM Ej5");
$display("A B | Y");
$display("----|--");
$monitor ("%b %b | %b", A35, B35, Y35);

A35 = 0; B35 = 0;

#1 B35=1;
#1 A35=1; B35=0;
#1 B35=1;
end 

KMap_BM T35 (A45, B45, Y45); //ecuación del K map BM

initial begin 
    #170
    
$display("Tabla K-Map BM Ej5");
$display("A B | Y");
$display("----|--");
$monitor ("%b %b | %b", A45, B45, Y45);

A45 = 0; B45 = 0;

#1 B45=1;
#1 A45=1; B45=0;
#1 B45=1;
#1 $finish; //esto voy acarreando
end 

initial begin //todo esto va de último
    $dumpfile("ModulosLab03_tb.vcd");
    $dumpvars(0,testbench);
    
end
endmodule

Lab #04/ModulosLab03_tb.vcd
$date
	Sun Aug 09 17:55:04 2020
$end
$version
	Icarus Verilog
$end
$timescale
	1ps
$end
$scope module testbench $end
$var wire 1 ! Y5 $end
$var wire 1 " Y45 $end
$var wire 1 # Y35 $end
$var wire 1 $ Y25 $end
$var wire 1 % Y15 $end
$var wire 1 & Y14 $end
$var wire 1 ' Y13 $end
$var wire 1 ( Y12 $end
$var wire 1 ) Y11 $end
$var wire 1 * Y05 $end
$var wire 1 + Y04 $end
$var wire 1 , Y03 $end
$var wire 1 - Y02 $end
$var wire 1 . Y01 $end
$var reg 1 / A01 $end
$var reg 1 0 A03 $end
$var reg 1 1 A04 $end
$var reg 1 2 A05 $end
$var reg 1 3 A11 $end
$var reg 1 4 A13 $end
$var reg 1 5 A14 $end
$var reg 1 6 A15 $end
$var reg 1 7 A25 $end
$var reg 1 8 A35 $end
$var reg 1 9 A45 $end
$var reg 1 : A5 $end
$var reg 1 ; B01 $end
$var reg 1 < B02 $end
$var reg 1 = B03 $end
$var reg 1 > B04 $end
$var reg 1 ? B05 $end
$var reg 1 @ B11 $end
$var reg 1 A B12 $end
$var reg 1 B B13 $end
$var reg 1 C B14 $end
$var reg 1 D B15 $end
$var reg 1 E B25 $end
$var reg 1 F B35 $end
$var reg 1 G B45 $end
$var reg 1 H B5 $end
$var reg 1 I C01 $end
$var reg 1 J C03 $end
$var reg 1 K C04 $end
$var reg 1 L C11 $end
$var reg 1 M C12 $end
$var reg 1 N C13 $end
$var reg 1 O C14 $end
$var reg 1 P D03 $end
$var reg 1 Q D04 $end
$var reg 1 R D11 $end
$var reg 1 S D13 $end
$scope module K0 $end
$var wire 1 6 A15 $end
$var wire 1 D B15 $end
$var wire 1 % Y15 $end
$upscope $end
$scope module T01 $end
$var wire 1 / A01 $end
$var wire 1 ; B01 $end
$var wire 1 I C01 $end
$var wire 1 . Y01 $end
$var wire 1 T notA01 $end
$var wire 1 U notB01 $end
$var wire 1 V notC01 $end
$var wire 1 W out01 $end
$var wire 1 X out02 $end
$var wire 1 Y out03 $end
$upscope $end
$scope module T02 $end
$var wire 1 < B02 $end
$var wire 1 - Y02 $end
$upscope $end
$scope module T03 $end
$var wire 1 0 A03 $end
$var wire 1 = B03 $end
$var wire 1 J C03 $end
$var wire 1 P D03 $end
$var wire 1 , Y03 $end
$upscope $end
$scope module T04 $end
$var wire 1 1 A04 $end
$var wire 1 > B04 $end
$var wire 1 K C04 $end
$var wire 1 Q D04 $end
$var wire 1 + Y04 $end
$upscope $end
$scope module T05 $end
$var wire 1 2 A05 $end
$var wire 1 ? B05 $end
$var wire 1 * Y05 $end
$upscope $end
$scope module T11 $end
$var wire 1 3 A11 $end
$var wire 1 @ B11 $end
$var wire 1 L C11 $end
$var wire 1 R D11 $end
$var wire 1 ) Y11 $end
$upscope $end
$scope module T12 $end
$var wire 1 A B12 $end
$var wire 1 M C12 $end
$var wire 1 ( Y12 $end
$var wire 1 Z notB12 $end
$upscope $end
$scope module T13 $end
$var wire 1 4 A13 $end
$var wire 1 B B13 $end
$var wire 1 N C13 $end
$var wire 1 S D13 $end
$var wire 1 ' Y13 $end
$upscope $end
$scope module T14 $end
$var wire 1 5 A14 $end
$var wire 1 C B14 $end
$var wire 1 O C14 $end
$var wire 1 & Y14 $end
$var wire 1 [ notA14 $end
$var wire 1 \ notC14 $end
$var wire 1 ] out11 $end
$upscope $end
$scope module T15 $end
$var wire 1 7 A25 $end
$var wire 1 E B25 $end
$var wire 1 $ Y25 $end
$upscope $end
$scope module T25 $end
$var wire 1 8 A35 $end
$var wire 1 F B35 $end
$var wire 1 # Y35 $end
$upscope $end
$scope module T35 $end
$var wire 1 9 A45 $end
$var wire 1 G B45 $end
$var wire 1 " Y45 $end
$upscope $end
$scope module T5 $end
$var wire 1 : A5 $end
$var wire 1 H B5 $end
$var wire 1 ! Y5 $end
$var wire 1 ^ notA5 $end
$var wire 1 _ notB5 $end
$var wire 1 ` out5 $end
$var wire 1 a out6 $end
$var wire 1 b out7 $end
$upscope $end
$upscope $end
$enddefinitions $end
#0
$dumpvars
xb
xa
x`
x_
x^
x]
x\
x[
xZ
0Y
0X
1W
1V
1U
1T
xS
xR
xQ
xP
xO
xN
xM
xL
xK
xJ
0I
xH
xG
xF
xE
xD
xC
xB
xA
x@
x?
x>
x=
x<
0;
x:
x9
x8
x7
x6
x5
x4
x3
x2
x1
x0
0/
1.
x-
x,
x+
x*
x)
x(
x'
x&
x%
x$
x#
x"
x!
$end
#1
0.
0W
0V
1I
#2
1.
1W
1V
0U
0I
1;
#3
0.
0W
0V
1I
#4
1.
1Y
1V
1U
0T
0I
0;
1/
#5
0V
1X
1I
#6
0.
0Y
1V
0X
0U
0I
1;
#7
1.
0V
1X
1I
#10
1-
0<
#11
0-
1<
#15
1,
0P
0J
0=
00
#16
0,
1P
#17
0P
1J
#18
1,
1P
#19
0,
0P
0J
1=
#20
1,
1P
#21
0P
1J
#22
0,
1P
#23
0P
0J
0=
10
#24
1,
1P
#25
0P
1J
#26
0,
1P
#27
1,
0P
0J
1=
#28
0,
1P
#29
0P
1J
#30
1,
1P
#35
0+
0Q
0K
0>
01
#36
1Q
#37
0Q
1K
#38
1Q
#39
0Q
0K
1>
#40
1Q
#41
0Q
1K
#42
1Q
#43
1+
0Q
0K
0>
11
#44
0+
1Q
#45
1+
0Q
1K
#46
1Q
#47
0Q
0K
1>
#48
1Q
#49
0Q
1K
#50
1Q
#55
1)
0R
0L
0@
03
#56
0)
1R
#57
0R
1L
#58
1R
#59
0R
0L
1@
#60
1R
#61
0R
1L
#62
1R
#63
1)
0R
0L
0@
13
#64
1R
#65
0R
1L
#66
1R
#67
1)
0R
0L
1@
#68
1R
#69
0R
1L
#70
0)
1R
#75
1(
1Z
0M
0A
#76
1M
#77
0(
0Z
0M
1A
#78
1(
1M
#85
0'
0S
0N
0B
04
#86
1'
1S
#87
0'
0S
1N
#88
1S
#89
1'
0S
0N
1B
#90
1S
#91
0S
1N
#92
1S
#93
0'
0S
0N
0B
14
#94
1'
1S
#95
0'
0S
1N
#96
1'
1S
#97
0S
0N
1B
#98
1S
#99
0S
1N
#100
1S
#107
1&
1]
1\
1[
0O
0C
05
#108
0&
0]
0\
1O
#109
1]
1\
1&
0O
1C
#110
0]
0\
1O
#111
1\
0&
0[
0O
0C
15
#112
0\
1O
#113
1\
1&
0O
1C
#114
0\
1O
#120
0!
1_
0`
1^
0a
0b
0H
0:
#121
1!
0_
1`
1H
#122
1a
1!
1_
0`
0^
0H
1:
#123
0a
0_
1b
1H
#130
0*
0?
02
#131
1*
1?
#132
0?
12
#133
1?
#140
0%
0D
06
#141
1%
1D
#142
0D
16
#143
1D
#150
0$
0E
07
#151
1$
1E
#152
0E
17
#153
1E
#160
0#
0F
08
#161
1F
#162
0F
18
#163
1#
1F
#170
0"
0G
09
#171
1G
#172
0G
19
#173
1"
1G
