Lab #05/Modulos_Muxes.v
//Nicole Prem 18337//
//para todas las variables de los muxes, de izquierd a derecha, d son las entradas, el siguiente dígito
//es del número del mux (si es 2:1 será 2) y el siguiente dígido es el número de la entrada
// en la implementación de los ejercicios, el tercer dígito es el número de tabla

//Mux 2:1

module mux2 (input wire d20, d21, s2, output wire y2);

assign y2 = s2 ? d20  : d21;
endmodule 

 //Mux 4:1
module mux4 (input wire d40, d41, d42, d43, input wire [1:0] s4, output wire y4);

wire low, high;

mux2 lowmux (d40, d41, s4 [0], low);
mux2 highmux (d42, d43, s4 [0], high);
mux2 finalmux (low, high, s4 [1], y4);
endmodule

//Mux 8:1
module mux8 (input wire d80, d81, d82, d83, d84, d85, d86, d87, input wire [2:0] s8, output wire y8);

wire low8, high8, final;

mux4 lowmux8  (d87, d86, d85, d84, s8[1:0], low8);
mux4 highmux8 (d83,d82, d81, d80, s8[1:0], high8);
mux2 muxfinal8 (low8, high8, s8[2], y8);
endmodule 

module mux2_T01 (input wire A201, B201, C201, output wire y201); //mux 2:1 de la tabla 01

mux2 M2_01 ((B201~^C201), (B201^C201), A201, y201);
endmodule 

module mux4_T01 (input wire d410, d411, d412, d413, input wire [1:0] AB01, output wire y401); //mux 4:1 de la tabla 01

mux4 M4_01 (d410, ~d411, ~d412, d413, AB01, y401);
endmodule

module mux8_T01 (input wire d810, d811, d812, d813, d814, d815, d816, d817, input wire [2:0] ABC01, output wire y801); //mux 8:1 de la tabla 01

mux8 M8_01 (~d810, d811, d812, ~d813, d814, ~d815, ~d816, d817, ABC01, y801);
endmodule

module mux2_T02 (input wire A202, B202, C202, output wire y202); //mux 2:1 de la tabla 02

mux2 M2_02 ((B202^C202),(~B202 & ~C202), A202, y202);
endmodule

module mux4_T02 (input wire d420, d421, d422, d423, input wire [1:0] AB02, output wire y402); //mux 4:1 de la tabla 02
wire d424;
assign d424 = 0;

mux4 M4_02 (~d420, d422, d424, ~d423, AB02, y402);
endmodule

module mux8_T02 (input wire d820, d821, d822, d823, d824, d825, d826, d827, input wire [2:0] ABC02, output wire y802); //mux 8:1 de la tabla 01

mux8 M8_01 (d820, ~d821, ~d822, ~d823, ~d824, d825, d826, ~d827, ABC02, y802);
endmodule

Lab #05/Modulos_Muxes_tb.v
//Nicole Prem 18337
//testbench

module testbench();

reg d20, d21, s2, d40, d41, d42, d43, d80, d81, d82, d83, d84, d85, d86, d87, A201, B201, C201, d410, d411, d412, d413, d810, d811, d812, d813, d814, d815, d816, d817,
A202, B202, C202, d420, d421, d422, d423, d820, d821, d822, d823, d824, d825, d826, d827; 
reg [1:0] s4;
reg [2:0] s8;
wire y2, y4, y8, y201, y401, y801, y202, y402, y802;


mux2 M2 (d20, d21, s2, y2); //mux 2:1
initial begin
$display("\n");
$display("Mux 2:1");
$display("S D0 D1 Y");
$display("-------|--");
$monitor ("%b %b %b | %b", s2, d20, d21, y2);

s2 = 0; d20 = 0; d21 = 0; //1

#1 d21=1; //2
#1 d20=1; d21=0; //3
#1 d21=1; //4
#1 s2=1; d21=0; d20=0; //5
#1 d21=1; //6
#1 d20=1; d21=0; //7
#1 d21=1; //8
end

mux4 M4 (d40, d41, d42, d43, s4, y4); //mux 4:1
initial begin
    #15
    $display("\n");
    $display("Mux 4:1");
    $display ("S D0 D1 D2 D3 Y");
    $display ("-----------|--");
    $monitor ("%b %b %b %b %b | %b", s4, d40, d41, d42, d43, y4);

s4 = 2'b00; d40 = 0; d41 = 0; d42 = 0; d43 = 0; //00
#1 d43 = 1;
#1 s4 = 2'b01; d42 = 1; d43 = 0; //01
#1 s4 = 2'b10; d41 = 1; d42 = 0; //10
#1 s4 = 2'b11; d40 = 1; d41 = 0; //11
end

mux8 M8 (d80, d81, d82, d83, d84, d85, d86, d87, s8, y8); //mux 8:1
initial begin
    #25
    $display("\n");
    $display ("Mux 8:1");
    $display ("S D0 D1 D2 D3 D4 D5 D6 D7 Y");
    $display ("----------------------|--");
    $monitor ("%b %b %b %b %b %b %b %b %b| %b", s8, d80, d81, d82, d83, d84, d85, d86, d87, y8);

s8 = 3'b000; d80 = 0; d81 = 0; d82 = 0; d83 = 0; d84 = 0; d85 = 0; d86 = 0; d87 = 0; //t1
#1 s8= 3'b000; d80 = 1; //t2
#1 s8= 3'b001; d81 = 1; d80 =0; //t3
#1 s8= 3'b010; d82 = 1; d81 = 0; //t4
#1 s8= 3'b011; d83 = 1; d82 = 0; //t5
#1 s8= 3'b100; d84 = 1; d83 = 0; //t6
#1 s8= 3'b101; d85 = 1; d84 = 0; //t7
#1 s8= 3'b110; d86 = 1; d85 = 0; //t8
#1 s8= 3'b111; d87 = 1; d86 = 0;
end

mux2_T01 M201 (A201, B201, C201, y201); //tb del mux 2:1 de la tabla 01
initial begin
    #40
$display("\n");
$display("Mux 2:1 Tabla 01");
$display("A B C Y");
$display("-------|--");
$monitor ("%b %b %b | %b", A201, B201, C201, y201);

A201 = 0; B201 = 0; C201 = 0; //1

#1 C201=1; //2
#1 B201=1; C201=0; //3
#1 C201=1; //4
#1 A201=1; B201=0; C201=0; //5
#1 C201=1; //6
#1 B201=1; C201=0; //7
#1 C201=1; //8
end

mux4_T01 M401 (d410, d411, d412, d413, s4, y401); //tb del mux 4:1 de la tabla 01

initial begin
    #55
$display("\n");
$display("Mux 4:1 Tabla 01");
$display("A B C Y");
$display("-----|--");
$monitor ("%b %b | %b", s4, d413, y401);

s4 = 2'b00; d410 = 0; d411 = 0; d412 = 0; d413 = 0; //t1

#1 d413 = 1; //t2
#1 s4 = 2'b01; d412 = 0; d413 = 0; $monitor ("%b %b | %b", s4, d412, y401); //t3
#1 s4 = 2'b01; d412 = 1; //t4
#1 s4 = 2'b10; d411 = 0;  $monitor ("%b %b | %b", s4, d411, y401); //t5
#1 s4 = 2'b10; d411 = 1; //t6 
#1 s4 = 2'b11; d410 = 0; $monitor ("%b %b | %b", s4, d410, y401); //t7
#1 s4 = 2'b11; d410 = 1; $monitor ("%b %b | %b", s4, d410, y401); //t8
end

mux8_T01 M801 (d810, d811, d812, d813, d814, d815, d816, d817, s8, y801); //mux 8:1 de la tabla 01

initial begin
    #70
$display("\n");
$display("Mux 8:1 Tabla 01");
$display("A B C Y");
$display("-----|--");
$monitor("%b | %b", s8, y801);

s8 = 3'b000; d810 = 1; d811 = 0; d812 = 0; d813 = 0; d814 = 0; d815 = 0; d816 = 0; d817 = 0; //t1
#1 s8= 3'b001; d811 = 1; d810 = 0; //t2
#1 s8= 3'b010; d812 = 1; d811 =0; //t3
#1 s8= 3'b011; d813 = 1; d812 = 0; //t4
#1 s8= 3'b100; d814 = 1; d813 = 0; //t5
#1 s8= 3'b101; d815 = 1; d814 = 0; //t6
#1 s8= 3'b110; d816 = 1; d815 = 0; //t7
#1 s8= 3'b111; d817 = 1; d816 = 0; //t8

end

mux2_T02 M202 (A202, B202, C202, y202); //tb del mux 2:1 de la tabla 02
initial begin
    #85
$display("\n");
$display("Mux 2:1 Tabla 02");
$display("A B C Y");
$display("-------|--");
$monitor ("%b %b %b | %b", A202, B202, C202, y202);

A202 = 0; B202 = 0; C202 = 0; //1

#1 C202=1; //2
#1 B202=1; C202=0; //3
#1 C202=1; //4
#1 A202=1; B202=0; C202=0; //5
#1 C202=1; //6
#1 B202=1; C202=0; //7
#1 C202=1; //8
end

mux4_T02 M402 (d420, d421, d422, d423, s4, y402); //tb del mux 4:1 de la tabla 02

initial begin
    #100
$display("\n");
$display("Mux 4:1 Tabla 02");
$display("A B C Y");
$display("-----|--");
$monitor ("%b %b | %b", s4, d423, y402);

s4 = 2'b00; d420 = 0; d421 = 0; d422 = 0; d423 = 0; //t1

#1 d423 = 1; //t2
#1 s4 = 2'b01; d422 = 0; d423 = 0; $monitor ("%b %b | %b", s4, d422, y402); //t3
#1 s4 = 2'b01; d422 = 1; //t4
#1 s4 = 2'b10; d421 = 0;  $monitor ("%b %b | %b", s4, d421, y402); //t5
#1 s4 = 2'b10; d421 = 1; //t6 
#1 s4 = 2'b11; d420 = 0; $monitor ("%b %b | %b", s4, d420, y402); //t7
#1 s4 = 2'b11; d420 = 1; $monitor ("%b %b | %b", s4, d420, y402); //t8
end

mux8_T02 M802 (d820, d821, d822, d823, d824, d825, d826, d827, s8, y802); //mux 8:1 de la tabla 01

initial begin
    #120
$display("\n");
$display("Mux 8:1 Tabla 02");
$display("A B C Y");
$display("-----|--");
$monitor("%b | %b", s8, y802);

s8 = 3'b000; d820 = 1; d821 = 0; d822 = 0; d823 = 0; d824 = 0; d825 = 0; d826 = 0; d827 = 0; //t1
#1 s8= 3'b001; d821 = 1; d820 = 0; //t2
#1 s8= 3'b010; d822 = 1; d821 =0; //t3
#1 s8= 3'b011; d823 = 1; d822 = 0; //t4
#1 s8= 3'b100; d824 = 1; d823 = 0; //t5
#1 s8= 3'b101; d825 = 1; d824 = 0; //t6
#1 s8= 3'b110; d826 = 1; d825 = 0; //t7
#1 s8= 3'b111; d827 = 1; d826 = 0; //t8
#1 $finish; //lo acarreo

end


initial begin
    $dumpfile("Modulos_Muxes_tb.vcd");
    $dumpvars(0, testbench);
end 

endmodule

Lab #05/Modulos_Muxes_tb.vcd
$date
	Sun Aug 16 11:31:11 2020
$end
$version
	Icarus Verilog
$end
$timescale
	1ps
$end
$scope module testbench $end
$var wire 1 ! y802 $end
$var wire 1 " y801 $end
$var wire 1 # y8 $end
$var wire 1 $ y402 $end
$var wire 1 % y401 $end
$var wire 1 & y4 $end
$var wire 1 ' y202 $end
$var wire 1 ( y201 $end
$var wire 1 ) y2 $end
$var reg 1 * A201 $end
$var reg 1 + A202 $end
$var reg 1 , B201 $end
$var reg 1 - B202 $end
$var reg 1 . C201 $end
$var reg 1 / C202 $end
$var reg 1 0 d20 $end
$var reg 1 1 d21 $end
$var reg 1 2 d40 $end
$var reg 1 3 d41 $end
$var reg 1 4 d410 $end
$var reg 1 5 d411 $end
$var reg 1 6 d412 $end
$var reg 1 7 d413 $end
$var reg 1 8 d42 $end
$var reg 1 9 d420 $end
$var reg 1 : d421 $end
$var reg 1 ; d422 $end
$var reg 1 < d423 $end
$var reg 1 = d43 $end
$var reg 1 > d80 $end
$var reg 1 ? d81 $end
$var reg 1 @ d810 $end
$var reg 1 A d811 $end
$var reg 1 B d812 $end
$var reg 1 C d813 $end
$var reg 1 D d814 $end
$var reg 1 E d815 $end
$var reg 1 F d816 $end
$var reg 1 G d817 $end
$var reg 1 H d82 $end
$var reg 1 I d820 $end
$var reg 1 J d821 $end
$var reg 1 K d822 $end
$var reg 1 L d823 $end
$var reg 1 M d824 $end
$var reg 1 N d825 $end
$var reg 1 O d826 $end
$var reg 1 P d827 $end
$var reg 1 Q d83 $end
$var reg 1 R d84 $end
$var reg 1 S d85 $end
$var reg 1 T d86 $end
$var reg 1 U d87 $end
$var reg 1 V s2 $end
$var reg 2 W s4 [1:0] $end
$var reg 3 X s8 [2:0] $end
$scope module M2 $end
$var wire 1 0 d20 $end
$var wire 1 1 d21 $end
$var wire 1 V s2 $end
$var wire 1 ) y2 $end
$upscope $end
$scope module M201 $end
$var wire 1 * A201 $end
$var wire 1 , B201 $end
$var wire 1 . C201 $end
$var wire 1 ( y201 $end
$scope module M2_01 $end
$var wire 1 Y d20 $end
$var wire 1 Z d21 $end
$var wire 1 * s2 $end
$var wire 1 ( y2 $end
$upscope $end
$upscope $end
$scope module M202 $end
$var wire 1 + A202 $end
$var wire 1 - B202 $end
$var wire 1 / C202 $end
$var wire 1 ' y202 $end
$scope module M2_02 $end
$var wire 1 [ d20 $end
$var wire 1 \ d21 $end
$var wire 1 + s2 $end
$var wire 1 ' y2 $end
$upscope $end
$upscope $end
$scope module M4 $end
$var wire 1 2 d40 $end
$var wire 1 3 d41 $end
$var wire 1 8 d42 $end
$var wire 1 = d43 $end
$var wire 2 ] s4 [1:0] $end
$var wire 1 & y4 $end
$var wire 1 ^ low $end
$var wire 1 _ high $end
$scope module finalmux $end
$var wire 1 ` s2 $end
$var wire 1 & y2 $end
$var wire 1 _ d21 $end
$var wire 1 ^ d20 $end
$upscope $end
$scope module highmux $end
$var wire 1 8 d20 $end
$var wire 1 = d21 $end
$var wire 1 a s2 $end
$var wire 1 _ y2 $end
$upscope $end
$scope module lowmux $end
$var wire 1 2 d20 $end
$var wire 1 3 d21 $end
$var wire 1 b s2 $end
$var wire 1 ^ y2 $end
$upscope $end
$upscope $end
$scope module M401 $end
$var wire 2 c AB01 [1:0] $end
$var wire 1 4 d410 $end
$var wire 1 5 d411 $end
$var wire 1 6 d412 $end
$var wire 1 7 d413 $end
$var wire 1 % y401 $end
$scope module M4_01 $end
$var wire 1 4 d40 $end
$var wire 1 d d41 $end
$var wire 1 e d42 $end
$var wire 1 7 d43 $end
$var wire 2 f s4 [1:0] $end
$var wire 1 % y4 $end
$var wire 1 g low $end
$var wire 1 h high $end
$scope module finalmux $end
$var wire 1 i s2 $end
$var wire 1 % y2 $end
$var wire 1 h d21 $end
$var wire 1 g d20 $end
$upscope $end
$scope module highmux $end
$var wire 1 e d20 $end
$var wire 1 7 d21 $end
$var wire 1 j s2 $end
$var wire 1 h y2 $end
$upscope $end
$scope module lowmux $end
$var wire 1 4 d20 $end
$var wire 1 d d21 $end
$var wire 1 k s2 $end
$var wire 1 g y2 $end
$upscope $end
$upscope $end
$upscope $end
$scope module M402 $end
$var wire 2 l AB02 [1:0] $end
$var wire 1 9 d420 $end
$var wire 1 : d421 $end
$var wire 1 ; d422 $end
$var wire 1 < d423 $end
$var wire 1 m d424 $end
$var wire 1 $ y402 $end
$scope module M4_02 $end
$var wire 1 n d40 $end
$var wire 1 ; d41 $end
$var wire 1 m d42 $end
$var wire 1 o d43 $end
$var wire 2 p s4 [1:0] $end
$var wire 1 $ y4 $end
$var wire 1 q low $end
$var wire 1 r high $end
$scope module finalmux $end
$var wire 1 s s2 $end
$var wire 1 $ y2 $end
$var wire 1 r d21 $end
$var wire 1 q d20 $end
$upscope $end
$scope module highmux $end
$var wire 1 m d20 $end
$var wire 1 o d21 $end
$var wire 1 t s2 $end
$var wire 1 r y2 $end
$upscope $end
$scope module lowmux $end
$var wire 1 n d20 $end
$var wire 1 ; d21 $end
$var wire 1 u s2 $end
$var wire 1 q y2 $end
$upscope $end
$upscope $end
$upscope $end
$scope module M8 $end
$var wire 1 > d80 $end
$var wire 1 ? d81 $end
$var wire 1 H d82 $end
$var wire 1 Q d83 $end
$var wire 1 R d84 $end
$var wire 1 S d85 $end
$var wire 1 T d86 $end
$var wire 1 U d87 $end
$var wire 3 v s8 [2:0] $end
$var wire 1 # y8 $end
$var wire 1 w low8 $end
$var wire 1 x high8 $end
$scope module highmux8 $end
$var wire 1 Q d40 $end
$var wire 1 H d41 $end
$var wire 1 ? d42 $end
$var wire 1 > d43 $end
$var wire 2 y s4 [1:0] $end
$var wire 1 x y4 $end
$var wire 1 z low $end
$var wire 1 { high $end
$scope module finalmux $end
$var wire 1 | s2 $end
$var wire 1 x y2 $end
$var wire 1 { d21 $end
$var wire 1 z d20 $end
$upscope $end
$scope module highmux $end
$var wire 1 ? d20 $end
$var wire 1 > d21 $end
$var wire 1 } s2 $end
$var wire 1 { y2 $end
$upscope $end
$scope module lowmux $end
$var wire 1 Q d20 $end
$var wire 1 H d21 $end
$var wire 1 ~ s2 $end
$var wire 1 z y2 $end
$upscope $end
$upscope $end
$scope module lowmux8 $end
$var wire 1 U d40 $end
$var wire 1 T d41 $end
$var wire 1 S d42 $end
$var wire 1 R d43 $end
$var wire 2 !" s4 [1:0] $end
$var wire 1 w y4 $end
$var wire 1 "" low $end
$var wire 1 #" high $end
$scope module finalmux $end
$var wire 1 $" s2 $end
$var wire 1 w y2 $end
$var wire 1 #" d21 $end
$var wire 1 "" d20 $end
$upscope $end
$scope module highmux $end
$var wire 1 S d20 $end
$var wire 1 R d21 $end
$var wire 1 %" s2 $end
$var wire 1 #" y2 $end
$upscope $end
$scope module lowmux $end
$var wire 1 U d20 $end
$var wire 1 T d21 $end
$var wire 1 &" s2 $end
$var wire 1 "" y2 $end
$upscope $end
$upscope $end
$scope module muxfinal8 $end
$var wire 1 w d20 $end
$var wire 1 x d21 $end
$var wire 1 '" s2 $end
$var wire 1 # y2 $end
$upscope $end
$upscope $end
$scope module M801 $end
$var wire 3 (" ABC01 [2:0] $end
$var wire 1 @ d810 $end
$var wire 1 A d811 $end
$var wire 1 B d812 $end
$var wire 1 C d813 $end
$var wire 1 D d814 $end
$var wire 1 E d815 $end
$var wire 1 F d816 $end
$var wire 1 G d817 $end
$var wire 1 " y801 $end
$scope module M8_01 $end
$var wire 1 )" d80 $end
$var wire 1 A d81 $end
$var wire 1 B d82 $end
$var wire 1 *" d83 $end
$var wire 1 D d84 $end
$var wire 1 +" d85 $end
$var wire 1 ," d86 $end
$var wire 1 G d87 $end
$var wire 3 -" s8 [2:0] $end
$var wire 1 " y8 $end
$var wire 1 ." low8 $end
$var wire 1 /" high8 $end
$scope module highmux8 $end
$var wire 1 *" d40 $end
$var wire 1 B d41 $end
$var wire 1 A d42 $end
$var wire 1 )" d43 $end
$var wire 2 0" s4 [1:0] $end
$var wire 1 /" y4 $end
$var wire 1 1" low $end
$var wire 1 2" high $end
$scope module finalmux $end
$var wire 1 3" s2 $end
$var wire 1 /" y2 $end
$var wire 1 2" d21 $end
$var wire 1 1" d20 $end
$upscope $end
$scope module highmux $end
$var wire 1 A d20 $end
$var wire 1 )" d21 $end
$var wire 1 4" s2 $end
$var wire 1 2" y2 $end
$upscope $end
$scope module lowmux $end
$var wire 1 *" d20 $end
$var wire 1 B d21 $end
$var wire 1 5" s2 $end
$var wire 1 1" y2 $end
$upscope $end
$upscope $end
$scope module lowmux8 $end
$var wire 1 G d40 $end
$var wire 1 ," d41 $end
$var wire 1 +" d42 $end
$var wire 1 D d43 $end
$var wire 2 6" s4 [1:0] $end
$var wire 1 ." y4 $end
$var wire 1 7" low $end
$var wire 1 8" high $end
$scope module finalmux $end
$var wire 1 9" s2 $end
$var wire 1 ." y2 $end
$var wire 1 8" d21 $end
$var wire 1 7" d20 $end
$upscope $end
$scope module highmux $end
$var wire 1 +" d20 $end
$var wire 1 D d21 $end
$var wire 1 :" s2 $end
$var wire 1 8" y2 $end
$upscope $end
$scope module lowmux $end
$var wire 1 G d20 $end
$var wire 1 ," d21 $end
$var wire 1 ;" s2 $end
$var wire 1 7" y2 $end
$upscope $end
$upscope $end
$scope module muxfinal8 $end
$var wire 1 ." d20 $end
$var wire 1 /" d21 $end
$var wire 1 <" s2 $end
$var wire 1 " y2 $end
$upscope $end
$upscope $end
$upscope $end
$scope module M802 $end
$var wire 3 =" ABC02 [2:0] $end
$var wire 1 I d820 $end
$var wire 1 J d821 $end
$var wire 1 K d822 $end
$var wire 1 L d823 $end
$var wire 1 M d824 $end
$var wire 1 N d825 $end
$var wire 1 O d826 $end
$var wire 1 P d827 $end
$var wire 1 ! y802 $end
$scope module M8_01 $end
$var wire 1 I d80 $end
$var wire 1 >" d81 $end
$var wire 1 ?" d82 $end
$var wire 1 @" d83 $end
$var wire 1 A" d84 $end
$var wire 1 N d85 $end
$var wire 1 O d86 $end
$var wire 1 B" d87 $end
$var wire 3 C" s8 [2:0] $end
$var wire 1 ! y8 $end
$var wire 1 D" low8 $end
$var wire 1 E" high8 $end
$scope module highmux8 $end
$var wire 1 @" d40 $end
$var wire 1 ?" d41 $end
$var wire 1 >" d42 $end
$var wire 1 I d43 $end
$var wire 2 F" s4 [1:0] $end
$var wire 1 E" y4 $end
$var wire 1 G" low $end
$var wire 1 H" high $end
$scope module finalmux $end
$var wire 1 I" s2 $end
$var wire 1 E" y2 $end
$var wire 1 H" d21 $end
$var wire 1 G" d20 $end
$upscope $end
$scope module highmux $end
$var wire 1 >" d20 $end
$var wire 1 I d21 $end
$var wire 1 J" s2 $end
$var wire 1 H" y2 $end
$upscope $end
$scope module lowmux $end
$var wire 1 @" d20 $end
$var wire 1 ?" d21 $end
$var wire 1 K" s2 $end
$var wire 1 G" y2 $end
$upscope $end
$upscope $end
$scope module lowmux8 $end
$var wire 1 B" d40 $end
$var wire 1 O d41 $end
$var wire 1 N d42 $end
$var wire 1 A" d43 $end
$var wire 2 L" s4 [1:0] $end
$var wire 1 D" y4 $end
$var wire 1 M" low $end
$var wire 1 N" high $end
$scope module finalmux $end
$var wire 1 O" s2 $end
$var wire 1 D" y2 $end
$var wire 1 N" d21 $end
$var wire 1 M" d20 $end
$upscope $end
$scope module highmux $end
$var wire 1 N d20 $end
$var wire 1 A" d21 $end
$var wire 1 P" s2 $end
$var wire 1 N" y2 $end
$upscope $end
$scope module lowmux $end
$var wire 1 B" d20 $end
$var wire 1 O d21 $end
$var wire 1 Q" s2 $end
$var wire 1 M" y2 $end
$upscope $end
$upscope $end
$scope module muxfinal8 $end
$var wire 1 D" d20 $end
$var wire 1 E" d21 $end
$var wire 1 R" s2 $end
$var wire 1 ! y2 $end
$upscope $end
$upscope $end
$upscope $end
$upscope $end
$enddefinitions $end
#0
$dumpvars
xR"
xQ"
xP"
xO"
xN"
xM"
bx L"
xK"
xJ"
xI"
xH"
xG"
bx F"
xE"
xD"
bx C"
xB"
xA"
x@"
x?"
x>"
bx ="
x<"
x;"
x:"
x9"
x8"
x7"
bx 6"
x5"
x4"
x3"
x2"
x1"
bx 0"
x/"
x."
bx -"
x,"
x+"
x*"
x)"
bx ("
x'"
x&"
x%"
x$"
x#"
x""
bx !"
x~
x}
x|
x{
xz
bx y
xx
xw
bx v
xu
xt
xs
xr
xq
bx p
xo
xn
0m
bx l
xk
xj
xi
xh
xg
bx f
xe
xd
bx c
xb
xa
x`
x_
x^
bx ]
x\
x[
xZ
xY
bx X
bx W
0V
xU
xT
xS
xR
xQ
xP
xO
xN
xM
xL
xK
xJ
xI
xH
xG
xF
xE
xD
xC
xB
xA
x@
x?
x>
x=
x<
x;
x:
x9
x8
x7
x6
x5
x4
x3
x2
01
00
x/
x.
x-
x,
x+
x*
0)
x(
x'
x&
x%
x$
x#
x"
x!
$end
#1
1)
11
#2
0)
01
10
#3
1)
11
#4
0)
00
01
1V
#5
11
#6
1)
01
10
#7
11
#15
0&
0_
0^
0b
0a
0`
0k
0j
0i
0u
0t
0s
0=
08
03
02
b0 W
b0 ]
b0 c
b0 f
b0 l
b0 p
#16
1&
1_
1=
#17
0$
0r
1b
1a
1k
1j
1u
1t
0=
18
b1 W
b1 ]
b1 c
b1 f
b1 l
b1 p
#18
1^
1&
xr
x$
0_
0b
0a
1`
0k
0j
1i
0u
0t
1s
08
13
b10 W
b10 ]
b10 c
b10 f
b10 l
b10 p
#19
0r
1b
1a
1k
1j
1u
1t
03
12
b11 W
b11 ]
b11 c
b11 f
b11 l
b11 p
#25
0#
0w
0x
0&"
0%"
0$"
0~
0}
0|
0;"
0:"
09"
05"
04"
03"
0Q"
0P"
0O"
0K"
0J"
0I"
0""
0#"
0z
0{
b0 !"
b0 y
0'"
b0 6"
b0 0"
0<"
b0 L"
b0 F"
0R"
0U
0T
0S
0R
0Q
0H
0?
0>
b0 X
b0 v
b0 ("
b0 -"
b0 ="
b0 C"
#26
1#
1x
1{
1>
#27
1#
1x
1&"
1%"
1~
1}
1;"
1:"
15"
14"
1Q"
1P"
1K"
1J"
1{
b1 !"
b1 y
b1 6"
b1 0"
b1 L"
b1 F"
0>
1?
b1 X
b1 v
b1 ("
b1 -"
b1 ="
b1 C"
#28
1#
1z
1x
0&"
0%"
1$"
0~
0}
1|
0;"
0:"
19"
05"
04"
13"
0Q"
0P"
1O"
0K"
0J"
1I"
0{
b10 !"
b10 y
b10 6"
b10 0"
b10 L"
b10 F"
0?
1H
b10 X
b10 v
b10 ("
b10 -"
b10 ="
b10 C"
#29
1#
1x
1&"
1%"
1~
1}
1;"
1:"
15"
14"
1Q"
1P"
1K"
1J"
1z
b11 !"
b11 y
b11 6"
b11 0"
b11 L"
b11 F"
0H
1Q
b11 X
b11 v
b11 ("
b11 -"
b11 ="
b11 C"
#30
1w
1#"
0x
0&"
0%"
0$"
0~
0}
0|
1#
0;"
0:"
09"
05"
04"
03"
0Q"
0P"
0O"
0K"
0J"
0I"
0z
b0 !"
b0 y
1'"
b0 6"
b0 0"
1<"
b0 L"
b0 F"
1R"
0Q
1R
b100 X
b100 v
b100 ("
b100 -"
b100 ="
b100 C"
#31
1#
1w
1&"
1%"
1~
1}
1;"
1:"
15"
14"
1Q"
1P"
1K"
1J"
1#"
b1 !"
b1 y
b1 6"
b1 0"
b1 L"
b1 F"
0R
1S
b101 X
b101 v
b101 ("
b101 -"
b101 ="
b101 C"
#32
1#
1""
1w
0&"
0%"
1$"
0~
0}
1|
0;"
0:"
19"
05"
04"
13"
0Q"
0P"
1O"
0K"
0J"
1I"
0#"
b10 !"
b10 y
b10 6"
b10 0"
b10 L"
b10 F"
0S
1T
b110 X
b110 v
b110 ("
b110 -"
b110 ="
b110 C"
#33
1#
1w
1&"
1%"
1~
1}
1;"
1:"
15"
14"
1Q"
1P"
1K"
1J"
1""
b11 !"
b11 y
b11 6"
b11 0"
b11 L"
b11 F"
0T
1U
b111 X
b111 v
b111 ("
b111 -"
b111 ="
b111 C"
#40
0(
1Y
0Z
0.
0,
0*
#41
1(
0Y
1Z
1.
#42
0.
1,
#43
0(
1Y
0Z
1.
#44
1(
0.
0,
1*
#45
0(
0Y
1Z
1.
#46
0.
1,
#47
1(
1Y
0Z
1.
#55
0%
1g
0^
0&
0h
xr
x$
1e
1d
0b
0a
0`
0k
0j
0i
0u
0t
0s
07
06
05
04
b0 W
b0 ]
b0 c
b0 f
b0 l
b0 p
#56
1%
1h
17
#57
0$
1^
0g
0r
1b
1a
1k
1j
1u
1t
07
b1 W
b1 ]
b1 c
b1 f
b1 l
b1 p
#58
0%
0h
0e
16
#59
1%
0^
0&
1g
xr
x$
0b
0a
1`
0k
0j
1i
0u
0t
1s
b10 W
b10 ]
b10 c
b10 f
b10 l
b10 p
#60
0%
0g
0d
15
#61
1&
1^
0r
1b
1a
1k
1j
1u
1t
b11 W
b11 ]
b11 c
b11 f
b11 l
b11 p
#62
1%
1g
14
#70
0"
0""
0w
0/"
0."
08"
01"
0&"
0%"
0$"
0~
0}
0|
0#
0;"
0:"
09"
05"
04"
03"
0Q"
0P"
0O"
0K"
0J"
0I"
17"
1,"
1+"
1*"
02"
0)"
b0 !"
b0 y
0'"
b0 6"
b0 0"
0<"
b0 L"
b0 F"
0R"
0G
0F
0E
0D
0C
0B
0A
1@
b0 X
b0 v
b0 ("
b0 -"
b0 ="
b0 C"
#71
1"
1."
1/"
1""
07"
18"
11"
12"
1&"
1%"
1~
1}
1;"
1:"
15"
14"
1Q"
1P"
1K"
1J"
1)"
b1 !"
b1 y
b1 6"
b1 0"
b1 L"
b1 F"
0@
1A
b1 X
b1 v
b1 ("
b1 -"
b1 ="
b1 C"
#72
0""
0w
17"
08"
1."
0&"
0%"
1$"
0~
0}
1|
0;"
0:"
19"
05"
04"
13"
0Q"
0P"
1O"
0K"
0J"
1I"
12"
b10 !"
b10 y
b10 6"
b10 0"
b10 L"
b10 F"
0A
1B
b10 X
b10 v
b10 ("
b10 -"
b10 ="
b10 C"
#73
1w
0."
0"
1""
07"
18"
02"
0/"
1&"
1%"
1~
1}
1;"
1:"
15"
14"
1Q"
1P"
1K"
1J"
01"
0*"
b11 !"
b11 y
b11 6"
b11 0"
b11 L"
b11 F"
0B
1C
b11 X
b11 v
b11 ("
b11 -"
b11 ="
b11 C"
#74
1"
1/"
0""
0w
17"
1."
12"
0&"
0%"
0$"
0~
0}
0|
0#
0;"
0:"
09"
05"
04"
03"
0Q"
0P"
0O"
0K"
0J"
0I"
1*"
b0 !"
b0 y
1'"
b0 6"
b0 0"
1<"
b0 L"
b0 F"
1R"
0C
1D
b100 X
b100 v
b100 ("
b100 -"
b100 ="
b100 C"
#75
0/"
0"
1""
07"
11"
02"
0."
1&"
1%"
1~
1}
1;"
1:"
15"
14"
1Q"
1P"
1K"
1J"
08"
0+"
b1 !"
b1 y
b1 6"
b1 0"
b1 L"
b1 F"
0D
1E
b101 X
b101 v
b101 ("
b101 -"
b101 ="
b101 C"
#76
0#
0""
0w
01"
12"
0/"
0&"
0%"
1$"
0~
0}
1|
0;"
0:"
19"
05"
04"
13"
0Q"
0P"
1O"
0K"
0J"
1I"
1+"
0,"
b10 !"
b10 y
b10 6"
b10 0"
b10 L"
b10 F"
0E
1F
b110 X
b110 v
b110 ("
b110 -"
b110 ="
b110 C"
#77
1#
1"
1w
1/"
1."
1""
18"
11"
02"
17"
1&"
1%"
1~
1}
1;"
1:"
15"
14"
1Q"
1P"
1K"
1J"
1,"
b11 !"
b11 y
b11 6"
b11 0"
b11 L"
b11 F"
0F
1G
b111 X
b111 v
b111 ("
b111 -"
b111 ="
b111 C"
#85
1'
1\
0[
0/
0-
0+
#86
0'
0\
1[
1/
#87
0/
1-
#88
0[
1/
#89
1\
0/
0-
1+
#90
1'
0\
1[
1/
#91
0/
1-
#92
0'
0[
1/
#100
0^
0&
0g
0%
0q
1r
1$
1o
1n
0b
0a
0`
0k
0j
0i
0u
0t
0s
0<
0;
0:
09
b0 W
b0 ]
b0 c
b0 f
b0 l
b0 p
#101
0$
0r
0o
1<
#102
1^
1g
1q
1o
1b
1a
1k
1j
1u
1t
0<
b1 W
b1 ]
b1 c
b1 f
b1 l
b1 p
#103
1;
#104
0^
0&
0g
0%
1r
1$
0b
0a
1`
0k
0j
1i
0u
0t
1s
b10 W
b10 ]
b10 c
b10 f
b10 l
b10 p
#105
1:
#106
1&
1%
1^
1g
0r
1b
1a
1k
1j
1u
1t
b11 W
b11 ]
b11 c
b11 f
b11 l
b11 p
#107
0$
0q
0n
19
